mymtools/__init__.py
mymtools/main.py
mymtools-0.0.1.dist-info/METADATA
mymtools-0.0.1.dist-info/WHEEL
mymtools-0.0.1.dist-info/top_level.txt
mymtools-0.0.1.dist-info/RECORD
